app/filetransfer/__init__.py
app/filetransfer/__main__.py
app/filetransfer/settings.py
app/filetransfer/urls.py
app/filetransfer/views.py
FiletransferApp-0.0.2b2.dist-info/LICENSE
FiletransferApp-0.0.2b2.dist-info/METADATA
FiletransferApp-0.0.2b2.dist-info/WHEEL
FiletransferApp-0.0.2b2.dist-info/top_level.txt
FiletransferApp-0.0.2b2.dist-info/RECORD
