Metadata-Version: 2.1
Name: FiletransferApp
Version: 0.0.2b2
Summary: A file useful simple transfer service app
Home-page: UNKNOWN
Author: jieshao
Author-email: 1806620741@qq.com
License: GNU General Public License v3 (GPLv3)
Project-URL: Documentation, https://github.com/LY1806620741/Filetransfer/blob/master/README.md
Project-URL: Release notes, https://github.com/LY1806620741/Filetransfer/releases
Project-URL: Funding, https://ly1806620741.github.io/donate-bitcoin/
Project-URL: Source, https://github.com/LY1806620741/Filetransfer
Platform: UNKNOWN
Classifier: Programming Language :: Python :: 3
Classifier: Operating System :: OS Independent
Classifier: License :: OSI Approved :: GNU General Public License v3 (GPLv3)
Requires-Python: >=3.6
Requires-Dist: Django (>=3.1.4)
